cnstats/__init__.py
cnstats/__main__.py
cnstats/common.py
cnstats/regcode.py
cnstats/stats.py
cnstats/zbcode.py
cn_stats-0.1.0.dist-info/LICENSE
cn_stats-0.1.0.dist-info/METADATA
cn_stats-0.1.0.dist-info/WHEEL
cn_stats-0.1.0.dist-info/top_level.txt
cn_stats-0.1.0.dist-info/RECORD
