Metadata-Version: 2.1
Name: cn-stats
Version: 0.1.0
Summary: 获取中国国家统计局网站数据。
Home-page: https://github.com/songjian/cnstats
Author: sj
Author-email: 724385768@qq.com
License: UNKNOWN
Platform: UNKNOWN
Classifier: Programming Language :: Python :: 3
Classifier: License :: OSI Approved :: MIT License
Classifier: Operating System :: OS Independent
Requires-Python: >=3
License-File: LICENSE
Requires-Dist: pandas (>=1.4.1)
Requires-Dist: requests (>=2.28.1)
